[
    {
      "name": "Bitcoin",
      "symbol": "₿",
      "rank": 1,
      "age": 3940,
      "color": "#fa9e32",
      "png32": "https://lcw.nyc3.cdn.digitaloceanspaces.com/production/currencies/32/btc.png",
      "png64": "https://lcw.nyc3.cdn.digitaloceanspaces.com/production/currencies/64/btc.png",
      "webp32": "https://lcw.nyc3.cdn.digitaloceanspaces.com/production/currencies/32/btc.webp",
      "webp64": "https://lcw.nyc3.cdn.digitaloceanspaces.com/production/currencies/64/btc.webp",
      "exchanges": 189,
      "markets": 3124,
      "pairs": 966,
      "categories": [],
      "allTimeHighUSD": 68780.77475755227,
      "circulatingSupply": 19626268,
      "totalSupply": 19626268,
      "maxSupply": 21000000,
      "links": {
        "website": "https://bitcoin.org/",
        "whitepaper": "https://bitcoin.org/bitcoin.pdf",
        "twitter": null,
        "reddit": "https://reddit.com/r/bitcoin",
        "telegram": null,
        "discord": null,
        "medium": null,
        "instagram": null,
        "tiktok": null,
        "youtube": null,
        "linkedin": null,
        "twitch": null,
        "spotify": null,
        "naver": null,
        "wechat": null,
        "soundcloud": null
      },
      "code": "BTC",
      "rate": 60155.32873375631,
      "volume": 26791703532,
      "cap": 984361923357,
      "delta": {
        "hour": 1.0005,
        "day": 1.0337,
        "week": 1.1735,
        "month": 1.1679,
        "quarter": 1.4168,
        "year": 2.2995
      }
    },
    {
      "name": "Ethereum",
      "symbol": "Ξ",
      "rank": 2,
      "age": 3111,
      "color": "#282a2a",
      "png32": "https://lcw.nyc3.cdn.digitaloceanspaces.com/production/currencies/32/eth.png",
      "png64": "https://lcw.nyc3.cdn.digitaloceanspaces.com/production/currencies/64/eth.png",
      "webp32": "https://lcw.nyc3.cdn.digitaloceanspaces.com/production/currencies/32/eth.webp",
      "webp64": "https://lcw.nyc3.cdn.digitaloceanspaces.com/production/currencies/64/eth.webp",
      "exchanges": 344,
      "markets": 5692,
      "pairs": 3075,
      "categories": [
        "smart_contract_platforms"
      ],
      "allTimeHighUSD": 4861.288700810894,
      "circulatingSupply": 118365744,
      "totalSupply": 118365744,
      "maxSupply": null,
      "links": {
        "website": "https://www.ethereum.org/",
        "whitepaper": "https://github.com/ethereum/wiki/wiki/White-Paper",
        "twitter": "https://twitter.com/ethereum",
        "reddit": "https://reddit.com/r/ethereum",
        "telegram": null,
        "discord": "https://discord.com/invite/CetY6Y4",
        "medium": null,
        "instagram": null,
        "tiktok": null,
        "youtube": null,
        "linkedin": null,
        "twitch": null,
        "spotify": null,
        "naver": null,
        "wechat": null,
        "soundcloud": null
      },
      "code": "ETH",
      "rate": 2677.662353932024,
      "volume": 12064622891,
      "cap": 316943496704,
      "delta": {
        "hour": 1.0029,
        "day": 1.0637,
        "week": 1.1578,
        "month": 1.0394,
        "quarter": 1.3593,
        "year": 1.7711
      }
    },
    {
      "name": "Tether",
      "rank": 3,
      "age": 3274,
      "color": "#e9f4f4",
      "png32": "https://lcw.nyc3.cdn.digitaloceanspaces.com/production/currencies/32/usdt.png",
      "png64": "https://lcw.nyc3.cdn.digitaloceanspaces.com/production/currencies/64/usdt.png",
      "webp32": "https://lcw.nyc3.cdn.digitaloceanspaces.com/production/currencies/32/usdt.webp",
      "webp64": "https://lcw.nyc3.cdn.digitaloceanspaces.com/production/currencies/64/usdt.webp",
      "exchanges": 309,
      "markets": 16053,
      "pairs": 4700,
      "categories": [
        "stablecoins",
        "asset_backed_tokens"
      ],
      "allTimeHighUSD": 1.08372533074166,
      "circulatingSupply": 96475135177,
      "totalSupply": 96475135177,
      "maxSupply": null,
      "links": {
        "website": "https://tether.to",
        "whitepaper": "https://tether.to/wp-content/uploads/2015/04/Tether-White-Paper.pdf",
        "twitter": "https://twitter.com/tether_to",
        "reddit": "https://reddit.com/r/Tether",
        "telegram": "https://t.me/OfficialTether",
        "discord": null,
        "medium": null,
        "instagram": null,
        "tiktok": null,
        "youtube": null,
        "linkedin": null,
        "twitch": null,
        "spotify": null,
        "naver": null,
        "wechat": null,
        "soundcloud": null
      },
      "code": "USDT",
      "rate": 1.0014524043312623,
      "volume": 48374557700,
      "cap": 96615256081,
      "delta": {
        "hour": 1.0002,
        "day": 1.0016,
        "week": 1.0007,
        "month": 0.999,
        "quarter": 1.0078,
        "year": 0.9998
      }
    },
    {
      "name": "Solana",
      "rank": 4,
      "age": 1401,
      "color": "#7370e8",
      "png32": "https://lcw.nyc3.cdn.digitaloceanspaces.com/production/currencies/32/sol.png",
      "png64": "https://lcw.nyc3.cdn.digitaloceanspaces.com/production/currencies/64/sol.png",
      "webp32": "https://lcw.nyc3.cdn.digitaloceanspaces.com/production/currencies/32/sol.webp",
      "webp64": "https://lcw.nyc3.cdn.digitaloceanspaces.com/production/currencies/64/sol.webp",
      "exchanges": 75,
      "markets": 1051,
      "pairs": 798,
      "categories": [
        "smart_contract_platforms"
      ],
      "allTimeHighUSD": 259.8360337991446,
      "circulatingSupply": 437308801,
      "totalSupply": 569374871,
      "maxSupply": null,
      "links": {
        "website": "https://solana.com/",
        "whitepaper": "https://solana.com/docs",
        "twitter": "https://twitter.com/solana",
        "reddit": "https://reddit.com/r/solana",
        "telegram": "https://t.me/solana",
        "discord": "https://discord.com/invite/kBbATFA7PW",
        "medium": "https://medium.com/solana-labs",
        "instagram": "https://www.instagram.com/solana_updates",
        "tiktok": null,
        "youtube": "https://youtube.com/@SolanaFndn",
        "linkedin": null,
        "twitch": null,
        "spotify": null,
        "naver": null,
        "wechat": null,
        "soundcloud": null
      },
      "code": "SOL",
      "rate": 114.41470620702458,
      "volume": 3491860807,
      "cap": 50034557988,
      "delta": {
        "hour": 1.0026,
        "day": 1.0596,
        "week": 1.1928,
        "month": 1.1883,
        "quarter": 2.0269,
        "year": 5.4714
      }
    },
    {
      "name": "BNB",
      "rank": 5,
      "age": 2393,
      "color": "#f4bc2c",
      "png32": "https://lcw.nyc3.cdn.digitaloceanspaces.com/production/currencies/32/bnb.png",
      "png64": "https://lcw.nyc3.cdn.digitaloceanspaces.com/production/currencies/64/bnb.png",
      "webp32": "https://lcw.nyc3.cdn.digitaloceanspaces.com/production/currencies/32/bnb.webp",
      "webp64": "https://lcw.nyc3.cdn.digitaloceanspaces.com/production/currencies/64/bnb.webp",
      "exchanges": 138,
      "markets": 3237,
      "pairs": 2366,
      "categories": [
        "cex",
        "smart_contract_platforms"
      ],
      "allTimeHighUSD": 691.55924082575,
      "circulatingSupply": 148930232,
      "totalSupply": 148930232,
      "maxSupply": 197192382,
      "links": {
        "website": "https://www.binance.com/en/bnb?ref=Y6TC8MN4",
        "whitepaper": "https://academy.binance.com/en/articles/what-is-bnb?ref=Y6TC8MN4",
        "twitter": "https://twitter.com/binance",
        "reddit": "https://reddit.com/r/binance",
        "telegram": "https://t.me/binanceexchange",
        "discord": "https://discord.com/invite/amjFE7Grgr",
        "medium": "https://medium.com/@binance",
        "instagram": "https://instagram.com/Binance",
        "tiktok": null,
        "youtube": null,
        "linkedin": null,
        "twitch": null,
        "spotify": null,
        "naver": null,
        "wechat": null,
        "soundcloud": null
      },
      "code": "BNB",
      "rate": 329.61384617367304,
      "volume": 896310535,
      "cap": 49089466581,
      "delta": {
        "hour": 1.0017,
        "day": 1.0278,
        "week": 1.0475,
        "month": 1.0378,
        "quarter": 1.3555,
        "year": 1.0623
      }
    },
    {
      "name": "XRP",
      "rank": 6,
      "age": 3844,
      "color": "#040404",
      "png32": "https://lcw.nyc3.cdn.digitaloceanspaces.com/production/currencies/32/xrp.png",
      "png64": "https://lcw.nyc3.cdn.digitaloceanspaces.com/production/currencies/64/xrp.png",
      "webp32": "https://lcw.nyc3.cdn.digitaloceanspaces.com/production/currencies/32/xrp.webp",
      "webp64": "https://lcw.nyc3.cdn.digitaloceanspaces.com/production/currencies/64/xrp.webp",
      "exchanges": 110,
      "markets": 412,
      "pairs": 193,
      "categories": [
        "smart_contract_platforms"
      ],
      "allTimeHighUSD": 3.91546307780967,
      "circulatingSupply": 54506969135,
      "totalSupply": 99987912526,
      "maxSupply": 100000000000,
      "links": {
        "website": "https://ripple.com/",
        "whitepaper": "https://interledger.org/interledger.pdf",
        "twitter": "https://twitter.com/Ripple",
        "reddit": "https://reddit.com/r/ripple",
        "telegram": "https://t.me/Ripple",
        "discord": null,
        "medium": null,
        "instagram": null,
        "tiktok": null,
        "youtube": null,
        "linkedin": null,
        "twitch": null,
        "spotify": null,
        "naver": null,
        "wechat": null,
        "soundcloud": null
      },
      "code": "XRP",
      "rate": 0.5323345887936096,
      "volume": 1072784457,
      "cap": 29015945001,
      "delta": {
        "hour": 0.998,
        "day": 1.0054,
        "week": 1.0482,
        "month": 0.9158,
        "quarter": 0.8519,
        "year": 1.427
      }
    },
    {
      "name": "USD Coin",
      "rank": 7,
      "age": 1953,
      "color": "#edf3f9",
      "png32": "https://lcw.nyc3.cdn.digitaloceanspaces.com/production/currencies/32/usdc.png",
      "png64": "https://lcw.nyc3.cdn.digitaloceanspaces.com/production/currencies/64/usdc.png",
      "webp32": "https://lcw.nyc3.cdn.digitaloceanspaces.com/production/currencies/32/usdc.webp",
      "webp64": "https://lcw.nyc3.cdn.digitaloceanspaces.com/production/currencies/64/usdc.webp",
      "exchanges": 257,
      "markets": 2074,
      "pairs": 1017,
      "categories": [
        "stablecoins",
        "asset_backed_tokens"
      ],
      "allTimeHighUSD": 1.087,
      "circulatingSupply": 27810874343,
      "totalSupply": 27810874343,
      "maxSupply": null,
      "links": {
        "website": "https://www.centre.io/usdc",
        "whitepaper": "https://www.centre.io/pdfs/centre-whitepaper.pdf",
        "twitter": "https://twitter.com/centre_io",
        "reddit": null,
        "telegram": null,
        "discord": null,
        "medium": null,
        "instagram": null,
        "tiktok": null,
        "youtube": null,
        "linkedin": "https://www.linkedin.com/company/centre-consortium/",
        "twitch": null,
        "spotify": null,
        "naver": null,
        "wechat": null,
        "soundcloud": null
      },
      "code": "USDC",
      "rate": 1.000703312308787,
      "volume": 3660449280,
      "cap": 27830434073,
      "delta": {
        "hour": 1.0002,
        "day": 1.0039,
        "week": 0.9979,
        "month": 0.9969,
        "quarter": 1.0079,
        "year": 0.9992
      }
    },
    {
      "name": "Cardano",
      "rank": 8,
      "age": 2325,
      "color": "#226ed8",
      "png32": "https://lcw.nyc3.cdn.digitaloceanspaces.com/production/currencies/32/ada.png",
      "png64": "https://lcw.nyc3.cdn.digitaloceanspaces.com/production/currencies/64/ada.png",
      "webp32": "https://lcw.nyc3.cdn.digitaloceanspaces.com/production/currencies/32/ada.webp",
      "webp64": "https://lcw.nyc3.cdn.digitaloceanspaces.com/production/currencies/64/ada.webp",
      "exchanges": 86,
      "markets": 256,
      "pairs": 88,
      "categories": [
        "smart_contract_platforms"
      ],
      "allTimeHighUSD": 3.0939096930263132,
      "circulatingSupply": 36613928911,
      "totalSupply": 36613928911,
      "maxSupply": 45000000000,
      "links": {
        "website": "https://www.cardano.org/",
        "whitepaper": "https://www.cardanohub.org/en/academic-papers/",
        "twitter": "https://twitter.com/Cardano",
        "reddit": "https://reddit.com/r/cardano",
        "telegram": "https://t.me/cardano",
        "discord": null,
        "medium": null,
        "instagram": null,
        "tiktok": null,
        "youtube": null,
        "linkedin": null,
        "twitch": null,
        "spotify": null,
        "naver": null,
        "wechat": null,
        "soundcloud": null
      },
      "code": "ADA",
      "rate": 0.5619772150713773,
      "volume": 448921230,
      "cap": 20576193802,
      "delta": {
        "hour": 0.9979,
        "day": 1.0353,
        "week": 1.1409,
        "month": 1.0255,
        "quarter": 1.588,
        "year": 1.5554
      }
    },
    {
      "name": "Avalanche",
      "rank": 9,
      "age": 1238,
      "color": "#ec4343",
      "png32": "https://lcw.nyc3.cdn.digitaloceanspaces.com/production/currencies/32/avax.png",
      "png64": "https://lcw.nyc3.cdn.digitaloceanspaces.com/production/currencies/64/avax.png",
      "webp32": "https://lcw.nyc3.cdn.digitaloceanspaces.com/production/currencies/32/avax.webp",
      "webp64": "https://lcw.nyc3.cdn.digitaloceanspaces.com/production/currencies/64/avax.webp",
      "exchanges": 85,
      "markets": 443,
      "pairs": 220,
      "categories": [
        "smart_contract_platforms"
      ],
      "allTimeHighUSD": 146.465715882705,
      "circulatingSupply": 367482155,
      "totalSupply": 377752194,
      "maxSupply": 720000000,
      "links": {
        "website": "https://www.avax.network/",
        "whitepaper": "https://docs.avax.network/",
        "twitter": "https://twitter.com/avalancheavax",
        "reddit": "https://reddit.com/r/Avax",
        "telegram": "https://t.me/avalancheavax",
        "discord": "https://discord.com/invite/RwXY7P6",
        "medium": "https://medium.com/avalancheavax",
        "instagram": null,
        "tiktok": null,
        "youtube": null,
        "linkedin": null,
        "twitch": null,
        "spotify": null,
        "naver": null,
        "wechat": null,
        "soundcloud": null
      },
      "code": "AVAX",
      "rate": 41.47964552425414,
      "volume": 669208384,
      "cap": 15243029526,
      "delta": {
        "hour": 0.9979,
        "day": 1.055,
        "week": 1.202,
        "month": 1.1444,
        "quarter": 2.4037,
        "year": 2.3844
      }
    },
    {
      "name": "Chainlink",
      "rank": 10,
      "age": 2336,
      "color": "#2959d9",
      "png32": "https://lcw.nyc3.cdn.digitaloceanspaces.com/production/currencies/32/link.png",
      "png64": "https://lcw.nyc3.cdn.digitaloceanspaces.com/production/currencies/64/link.png",
      "webp32": "https://lcw.nyc3.cdn.digitaloceanspaces.com/production/currencies/32/link.webp",
      "webp64": "https://lcw.nyc3.cdn.digitaloceanspaces.com/production/currencies/64/link.webp",
      "exchanges": 153,
      "markets": 335,
      "pairs": 72,
      "categories": [
        "oracle",
        "token_bridges",
        "security",
        "analytics"
      ],
      "allTimeHighUSD": 52.85091701629316,
      "circulatingSupply": 587099970,
      "totalSupply": 1000000000,
      "maxSupply": 1000000000,
      "links": {
        "website": "https://chain.link/",
        "whitepaper": "https://research.chain.link/whitepaper-v2.pdf",
        "twitter": "https://twitter.com/chainlink",
        "reddit": "https://reddit.com/r/chainlink",
        "telegram": "https://t.me/chainlinkofficial",
        "discord": "https://discord.gg/aSK4zew",
        "medium": null,
        "instagram": null,
        "tiktok": null,
        "youtube": "https://www.youtube.com/@chainlink",
        "linkedin": null,
        "twitch": null,
        "spotify": null,
        "naver": null,
        "wechat": null,
        "soundcloud": null
      },
      "code": "LINK",
      "rate": 20.27816124638941,
      "volume": 938201892,
      "cap": 11905307859,
      "delta": {
        "hour": 0.995,
        "day": 1.0067,
        "week": 1.0622,
        "month": 1.406,
        "quarter": 1.4505,
        "year": 3.0131
      }
    },
    {
      "name": "Arbitrum",
      "rank": 11,
      "age": 326,
      "color": "#806418",
      "png32": "https://lcw.nyc3.cdn.digitaloceanspaces.com/production/currencies/32/arb.png",
      "png64": "https://lcw.nyc3.cdn.digitaloceanspaces.com/production/currencies/64/arb.png",
      "webp32": "https://lcw.nyc3.cdn.digitaloceanspaces.com/production/currencies/32/arb.webp",
      "webp64": "https://lcw.nyc3.cdn.digitaloceanspaces.com/production/currencies/64/arb.webp",
      "exchanges": 72,
      "markets": 159,
      "pairs": 45,
      "categories": [
        "governance"
      ],
      "allTimeHighUSD": 11.6446,
      "circulatingSupply": 5478760022,
      "totalSupply": 9999999999,
      "maxSupply": null,
      "links": {
        "website": "https://arbitrum.foundation",
        "whitepaper": "https://docs.arbitrum.foundation/",
        "twitter": "https://twitter.com/arbitrum",
        "reddit": null,
        "telegram": null,
        "discord": "https://discord.com/invite/arbitrum",
        "medium": " https://medium.com/offchainlabs",
        "instagram": null,
        "tiktok": null,
        "youtube": null,
        "linkedin": null,
        "twitch": null,
        "spotify": null,
        "naver": null,
        "wechat": null,
        "soundcloud": null
      },
      "code": "ARB",
      "rate": 2.1015737084210557,
      "volume": 585304109,
      "cap": 11514018017,
      "delta": {
        "hour": 1.0054,
        "day": 1.0681,
        "week": 1.2045,
        "month": 0.969,
        "quarter": 1.9558,
        "year": null
      }
    },
    {
      "name": "TRON",
      "rank": 12,
      "age": 2344,
      "color": "#c43429",
      "png32": "https://lcw.nyc3.cdn.digitaloceanspaces.com/production/currencies/32/trx.png",
      "png64": "https://lcw.nyc3.cdn.digitaloceanspaces.com/production/currencies/64/trx.png",
      "webp32": "https://lcw.nyc3.cdn.digitaloceanspaces.com/production/currencies/32/trx.webp",
      "webp64": "https://lcw.nyc3.cdn.digitaloceanspaces.com/production/currencies/64/trx.webp",
      "exchanges": 84,
      "markets": 237,
      "pairs": 52,
      "categories": [
        "storage",
        "smart_contract_platforms"
      ],
      "allTimeHighUSD": 0.2947430746031121,
      "circulatingSupply": 88076899341,
      "totalSupply": 88076899341,
      "maxSupply": null,
      "links": {
        "website": "https://tron.network/",
        "whitepaper": "https://o836fhe91.qnssl.com/tron/whitebook/TronWhitepaper_en.pdf",
        "twitter": "https://twitter.com/trondao",
        "reddit": "https://reddit.com/r/Tronix",
        "telegram": "https://t.me/tronnetworkEN",
        "discord": "https://discord.com/invite/ezNzd9W",
        "medium": "https://tronfoundation.medium.com/",
        "instagram": "https://instagram.com/tronfoundation",
        "tiktok": null,
        "youtube": null,
        "linkedin": null,
        "twitch": null,
        "spotify": null,
        "naver": null,
        "wechat": null,
        "soundcloud": null
      },
      "code": "TRX",
      "rate": 0.1270359753345485,
      "volume": 247667291,
      "cap": 11188934812,
      "delta": {
        "hour": 0.9998,
        "day": 1.0009,
        "week": 1.0447,
        "month": 1.0756,
        "quarter": 1.2249,
        "year": 1.9168
      }
    },
    {
      "name": "OKB",
      "rank": 13,
      "age": 1748,
      "color": "#050505",
      "png32": "https://lcw.nyc3.cdn.digitaloceanspaces.com/production/currencies/32/okb.png",
      "png64": "https://lcw.nyc3.cdn.digitaloceanspaces.com/production/currencies/64/okb.png",
      "webp32": "https://lcw.nyc3.cdn.digitaloceanspaces.com/production/currencies/32/okb.webp",
      "webp64": "https://lcw.nyc3.cdn.digitaloceanspaces.com/production/currencies/64/okb.webp",
      "exchanges": 12,
      "markets": 16,
      "pairs": 4,
      "categories": [
        "cex"
      ],
      "allTimeHighUSD": 64.44692623068303,
      "circulatingSupply": 219289286,
      "totalSupply": 219289500,
      "maxSupply": 300000000,
      "links": {
        "website": "https://www.okx.com/",
        "whitepaper": "https://okexchain-docs.readthedocs.io/en/latest/",
        "twitter": "https://twitter.com/okx",
        "reddit": "https://reddit.com/r/OKX",
        "telegram": "https://t.me/OKXOfficial_English",
        "discord": "https://discord.com/invite/2rynEUqJxP",
        "medium": "https://medium.com/okex-blog",
        "instagram": "https://www.instagram.com/okx_official/",
        "tiktok": "https://www.tiktok.com/@okx",
        "youtube": "https://www.youtube.com/@OKXCryptoExchange",
        "linkedin": "https://www.linkedin.com/company/okxofficial/",
        "twitch": null,
        "spotify": null,
        "naver": null,
        "wechat": null,
        "soundcloud": null
      },
      "code": "OKB",
      "rate": 50.65484284162531,
      "volume": 6299269,
      "cap": 11108064319,
      "delta": {
        "hour": 1.0007,
        "day": 1.0186,
        "week": 1.0442,
        "month": 0.9398,
        "quarter": 0.8613,
        "year": 1.2546
      }
    },
    {
      "name": "Dogecoin",
      "symbol": "Ɖ",
      "rank": 14,
      "age": 3711,
      "color": "#eee0b6",
      "png32": "https://lcw.nyc3.cdn.digitaloceanspaces.com/production/currencies/32/doge.png",
      "png64": "https://lcw.nyc3.cdn.digitaloceanspaces.com/production/currencies/64/doge.png",
      "webp32": "https://lcw.nyc3.cdn.digitaloceanspaces.com/production/currencies/32/doge.webp",
      "webp64": "https://lcw.nyc3.cdn.digitaloceanspaces.com/production/currencies/64/doge.webp",
      "exchanges": 102,
      "markets": 287,
      "pairs": 133,
      "categories": [
        "meme",
        "wallets",
        "charity"
      ],
      "allTimeHighUSD": 0.7371712183910056,
      "circulatingSupply": 132670764299,
      "totalSupply": 132670764299,
      "maxSupply": null,
      "links": {
        "website": "http://dogecoin.com/",
        "whitepaper": "https://dogecoin.com/dogepedia/",
        "twitter": "https://twitter.com/dogecoin",
        "reddit": "https://reddit.com/r/dogecoin",
        "telegram": null,
        "discord": "https://discord.com/invite/dogecoin",
        "medium": null,
        "instagram": null,
        "tiktok": null,
        "youtube": null,
        "linkedin": null,
        "twitch": null,
        "spotify": null,
        "naver": null,
        "wechat": null,
        "soundcloud": null
      },
      "code": "DOGE",
      "rate": 0.08289011166549483,
      "volume": 302571880,
      "cap": 10997094467,
      "delta": {
        "hour": 1.0001,
        "day": 1.0207,
        "week": 1.0565,
        "month": 1.0221,
        "quarter": 1.1503,
        "year": 1.0186
      }
    },
    {
      "name": "Polkadot",
      "rank": 15,
      "age": 1268,
      "color": "#e4047c",
      "png32": "https://lcw.nyc3.cdn.digitaloceanspaces.com/production/currencies/32/dot.png",
      "png64": "https://lcw.nyc3.cdn.digitaloceanspaces.com/production/currencies/64/dot.png",
      "webp32": "https://lcw.nyc3.cdn.digitaloceanspaces.com/production/currencies/32/dot.webp",
      "webp64": "https://lcw.nyc3.cdn.digitaloceanspaces.com/production/currencies/64/dot.webp",
      "exchanges": 84,
      "markets": 160,
      "pairs": 34,
      "categories": [
        "smart_contract_platforms"
      ],
      "allTimeHighUSD": 55.06538188283951,
      "circulatingSupply": 1353764717,
      "totalSupply": 1410442485,
      "maxSupply": null,
      "links": {
        "website": "https://polkadot.network/",
        "whitepaper": "https://polkadot.network/PolkaDotPaper.pdf",
        "twitter": "https://twitter.com/Polkadot",
        "reddit": "https://reddit.com/r/dot",
        "telegram": "https://t.me/PolkadotOfficial",
        "discord": "https://discord.com/invite/wGUDt2p",
        "medium": "https://medium.com/polkadot-network",
        "instagram": null,
        "tiktok": null,
        "youtube": null,
        "linkedin": null,
        "twitch": null,
        "spotify": null,
        "naver": null,
        "wechat": null,
        "soundcloud": null
      },
      "code": "DOT",
      "rate": 7.406452484364358,
      "volume": 263145732,
      "cap": 10026594051,
      "delta": {
        "hour": 0.9962,
        "day": 1.0385,
        "week": 1.1033,
        "month": 0.9767,
        "quarter": 1.4336,
        "year": 1.2048
      }
    },
    {
      "name": "Dai",
      "rank": 16,
      "age": 2239,
      "color": "#fcb934",
      "png32": "https://lcw.nyc3.cdn.digitaloceanspaces.com/production/currencies/32/dai.png",
      "png64": "https://lcw.nyc3.cdn.digitaloceanspaces.com/production/currencies/64/dai.png",
      "webp32": "https://lcw.nyc3.cdn.digitaloceanspaces.com/production/currencies/32/dai.webp",
      "webp64": "https://lcw.nyc3.cdn.digitaloceanspaces.com/production/currencies/64/dai.webp",
      "exchanges": 134,
      "markets": 402,
      "pairs": 148,
      "categories": [
        "stablecoins"
      ],
      "allTimeHighUSD": 1.1438930398132303,
      "circulatingSupply": 9359045406,
      "totalSupply": 10931954334,
      "maxSupply": null,
      "links": {
        "website": "http://www.makerdao.com/",
        "whitepaper": "https://makerdao.com/whitepaper/",
        "twitter": "https://twitter.com/makerDAO",
        "reddit": "https://reddit.com/r/makerDAO",
        "telegram": "https://t.me/makerdaoOfficial",
        "discord": null,
        "medium": null,
        "instagram": null,
        "tiktok": null,
        "youtube": null,
        "linkedin": null,
        "twitch": null,
        "spotify": null,
        "naver": null,
        "wechat": null,
        "soundcloud": null
      },
      "code": "DAI",
      "rate": 1.0008095449640824,
      "volume": 72996768,
      "cap": 9366621974,
      "delta": {
        "hour": 1.0001,
        "day": 1.0038,
        "week": 0.9991,
        "month": 0.9974,
        "quarter": 1.0056,
        "year": 0.9997
      }
    },
    {
      "name": "Polygon",
      "rank": 17,
      "age": 1750,
      "color": "#8444e4",
      "png32": "https://lcw.nyc3.cdn.digitaloceanspaces.com/production/currencies/32/matic.png",
      "png64": "https://lcw.nyc3.cdn.digitaloceanspaces.com/production/currencies/64/matic.png",
      "webp32": "https://lcw.nyc3.cdn.digitaloceanspaces.com/production/currencies/32/matic.webp",
      "webp64": "https://lcw.nyc3.cdn.digitaloceanspaces.com/production/currencies/64/matic.webp",
      "exchanges": 125,
      "markets": 639,
      "pairs": 296,
      "categories": [
        "smart_contract_platforms"
      ],
      "allTimeHighUSD": 2.920098783754804,
      "circulatingSupply": 9634695185,
      "totalSupply": 10000000000,
      "maxSupply": 10000000000,
      "links": {
        "website": "https://polygon.technology/",
        "whitepaper": "https://polygon.technology/lightpaper-polygon.pdf",
        "twitter": "https://twitter.com/0xPolygon",
        "reddit": "https://reddit.com/r/0xPolygon",
        "telegram": "https://t.me/maticnetwork",
        "discord": "https://discord.gg/tuETxzrh",
        "medium": "https://polygontech.medium.com/",
        "instagram": null,
        "tiktok": null,
        "youtube": null,
        "linkedin": null,
        "twitch": null,
        "spotify": null,
        "naver": null,
        "wechat": null,
        "soundcloud": null
      },
      "code": "MATIC",
      "rate": 0.8818247623495563,
      "volume": 323336202,
      "cap": 8496112792,
      "delta": {
        "hour": 1.0037,
        "day": 1.0519,
        "week": 1.1258,
        "month": 0.999,
        "quarter": 0.9604,
        "year": 0.721
      }
    },
    {
      "name": "Wrapped Bitcoin",
      "rank": 18,
      "age": 1838,
      "color": "#f09444",
      "png32": "https://lcw.nyc3.cdn.digitaloceanspaces.com/production/currencies/32/wbtc.png",
      "png64": "https://lcw.nyc3.cdn.digitaloceanspaces.com/production/currencies/64/wbtc.png",
      "webp32": "https://lcw.nyc3.cdn.digitaloceanspaces.com/production/currencies/32/wbtc.webp",
      "webp64": "https://lcw.nyc3.cdn.digitaloceanspaces.com/production/currencies/64/wbtc.webp",
      "exchanges": 123,
      "markets": 313,
      "pairs": 90,
      "categories": [
        "wrapped_tokens",
        "asset_backed_tokens"
      ],
      "allTimeHighUSD": 69231.2862532693,
      "circulatingSupply": 156932,
      "totalSupply": 156932,
      "maxSupply": null,
      "links": {
        "website": "https://www.wbtc.network/",
        "whitepaper": "https://wbtc.network/assets/wrapped-tokens-whitepaper.pdf",
        "twitter": "https://twitter.com/WrappedBTC",
        "reddit": null,
        "telegram": null,
        "discord": null,
        "medium": null,
        "instagram": null,
        "tiktok": null,
        "youtube": null,
        "linkedin": null,
        "twitch": null,
        "spotify": null,
        "naver": null,
        "wechat": null,
        "soundcloud": null
      },
      "code": "WBTC",
      "rate": 49969.29914975451,
      "volume": 108213006,
      "cap": 7841782054,
      "delta": {
        "hour": 1.001,
        "day": 1.0368,
        "week": 1.1725,
        "month": 1.1666,
        "quarter": 1.4158,
        "year": 2.293
      }
    },
    {
      "name": "Toncoin",
      "rank": 19,
      "age": 899,
      "color": "#87c1ec",
      "png32": "https://lcw.nyc3.cdn.digitaloceanspaces.com/production/currencies/32/toncoin.png",
      "png64": "https://lcw.nyc3.cdn.digitaloceanspaces.com/production/currencies/64/toncoin.png",
      "webp32": "https://lcw.nyc3.cdn.digitaloceanspaces.com/production/currencies/32/toncoin.webp",
      "webp64": "https://lcw.nyc3.cdn.digitaloceanspaces.com/production/currencies/64/toncoin.webp",
      "exchanges": 25,
      "markets": 60,
      "pairs": 31,
      "categories": [
        "smart_contract_platforms",
        "social_media",
        "governance",
        "dns",
        "storage"
      ],
      "allTimeHighUSD": 98.783104434167,
      "circulatingSupply": 3458322543,
      "totalSupply": 5102609651,
      "maxSupply": null,
      "links": {
        "website": "https://ton.org/",
        "whitepaper": "https://ton.org/docs/",
        "twitter": "https://twitter.com/ton_blockchain",
        "reddit": "https://reddit.com/r/TONcoin",
        "telegram": "https://t.me/tonblockchain",
        "discord": null,
        "medium": null,
        "instagram": null,
        "tiktok": null,
        "youtube": null,
        "linkedin": "https://www.linkedin.com/company/ton-blockchain/",
        "twitch": null,
        "spotify": null,
        "naver": null,
        "wechat": null,
        "soundcloud": null
      },
      "code": "TONCOIN",
      "rate": 2.2310500577139103,
      "volume": 41018095,
      "cap": 7715690709,
      "delta": {
        "hour": 0.9996,
        "day": 1.014,
        "week": 1.0106,
        "month": 1.0213,
        "quarter": 0.9754,
        "year": 0.9744
      }
    },
    {
      "name": "Internet Computer",
      "rank": 20,
      "age": 1007,
      "color": "#ea594e",
      "png32": "https://lcw.nyc3.cdn.digitaloceanspaces.com/production/currencies/32/icp.png",
      "png64": "https://lcw.nyc3.cdn.digitaloceanspaces.com/production/currencies/64/icp.png",
      "webp32": "https://lcw.nyc3.cdn.digitaloceanspaces.com/production/currencies/32/icp.webp",
      "webp64": "https://lcw.nyc3.cdn.digitaloceanspaces.com/production/currencies/64/icp.webp",
      "exchanges": 39,
      "markets": 67,
      "pairs": 16,
      "categories": [
        "cloud_hosting",
        "storage",
        "governance"
      ],
      "allTimeHighUSD": 494.5636424153892,
      "circulatingSupply": 457882995,
      "totalSupply": 514210337,
      "maxSupply": null,
      "links": {
        "website": "https://internetcomputer.org/",
        "whitepaper": "https://internetcomputer.org/whitepaper.pdf",
        "twitter": "https://twitter.com/dfinity",
        "reddit": "https://reddit.com/r/dfinity",
        "telegram": "https://t.me/dfinity/",
        "discord": "https://discord.com/invite/cE92CymEmJ",
        "medium": "https://medium.com/dfinity-network-blog",
        "instagram": null,
        "tiktok": null,
        "youtube": null,
        "linkedin": null,
        "twitch": null,
        "spotify": null,
        "naver": null,
        "wechat": null,
        "soundcloud": null
      },
      "code": "ICP",
      "rate": 13.31623117343672,
      "volume": 153728212,
      "cap": 6097275812,
      "delta": {
        "hour": 0.9947,
        "day": 1.0132,
        "week": 1.085,
        "month": 0.9866,
        "quarter": 3.1594,
        "year": 2.419
      }
    },
    {
      "name": "Shiba Inu",
      "rank": 21,
      "age": 1104,
      "color": "#faa00d",
      "png32": "https://lcw.nyc3.cdn.digitaloceanspaces.com/production/currencies/32/shib.png",
      "png64": "https://lcw.nyc3.cdn.digitaloceanspaces.com/production/currencies/64/shib.png",
      "webp32": "https://lcw.nyc3.cdn.digitaloceanspaces.com/production/currencies/32/shib.webp",
      "webp64": "https://lcw.nyc3.cdn.digitaloceanspaces.com/production/currencies/64/shib.webp",
      "exchanges": 80,
      "markets": 126,
      "pairs": 30,
      "categories": [
        "meme",
        "metaverse",
        "nfts",
        "dex",
        "yield_farming"
      ],
      "allTimeHighUSD": 0.00008877244256117385,
      "circulatingSupply": 589237041325323,
      "totalSupply": 589534326253386,
      "maxSupply": null,
      "links": {
        "website": "https://shibatoken.com/",
        "whitepaper": "https://github.com/shytoshikusama/shibawoofpaper/blob/main/SHIBAINU_Ecosystem_WOOF_Paper.pdf",
        "twitter": "https://twitter.com/shibtoken",
        "reddit": "https://reddit.com/r/SHIBArmy",
        "telegram": "https://t.me/shibainuthedogecoinkiller",
        "discord": "https://discord.com/invite/shibatoken",
        "medium": "https://allhailtheshiba.medium.com",
        "instagram": "https://www.instagram.com/shibatoken_official/",
        "tiktok": null,
        "youtube": null,
        "linkedin": null,
        "twitch": null,
        "spotify": null,
        "naver": null,
        "wechat": null,
        "soundcloud": null
      },
      "code": "SHIB",
      "rate": 0.000009693508131059241,
      "volume": 140398805,
      "cap": 5711774051,
      "delta": {
        "hour": 0.9989,
        "day": 1.0271,
        "week": 1.0902,
        "month": 0.9863,
        "quarter": 1.1645,
        "year": 0.7619
      }
    },
    {
      "name": "Bitcoin Cash",
      "rank": 22,
      "age": 2395,
      "color": "#f1f9f7",
      "png32": "https://lcw.nyc3.cdn.digitaloceanspaces.com/production/currencies/32/bch.png",
      "png64": "https://lcw.nyc3.cdn.digitaloceanspaces.com/production/currencies/64/bch.png",
      "webp32": "https://lcw.nyc3.cdn.digitaloceanspaces.com/production/currencies/32/bch.webp",
      "webp64": "https://lcw.nyc3.cdn.digitaloceanspaces.com/production/currencies/64/bch.webp",
      "exchanges": 89,
      "markets": 162,
      "pairs": 31,
      "categories": [
        "smart_contract_platforms"
      ],
      "allTimeHighUSD": 4355.62,
      "circulatingSupply": 19640274,
      "totalSupply": 19640274,
      "maxSupply": 21000000,
      "links": {
        "website": "https://www.bitcoincash.org/",
        "whitepaper": "https://www.bitcoincash.org/bitcoin.pdf",
        "twitter": null,
        "reddit": "https://reddit.com/r/Bitcoincash",
        "telegram": null,
        "discord": null,
        "medium": null,
        "instagram": null,
        "tiktok": null,
        "youtube": null,
        "linkedin": null,
        "twitch": null,
        "spotify": null,
        "naver": null,
        "wechat": null,
        "soundcloud": null
      },
      "code": "BCH",
      "rate": 278.84059715161646,
      "volume": 372066003,
      "cap": 5476505730,
      "delta": {
        "hour": 0.9943,
        "day": 1.0172,
        "week": 1.1826,
        "month": 1.0765,
        "quarter": 1.2143,
        "year": 2.2105
      }
    },
    {
      "name": "Litecoin",
      "rank": 23,
      "age": 3940,
      "color": "#345c9c",
      "png32": "https://lcw.nyc3.cdn.digitaloceanspaces.com/production/currencies/32/ltc.png",
      "png64": "https://lcw.nyc3.cdn.digitaloceanspaces.com/production/currencies/64/ltc.png",
      "webp32": "https://lcw.nyc3.cdn.digitaloceanspaces.com/production/currencies/32/ltc.webp",
      "webp64": "https://lcw.nyc3.cdn.digitaloceanspaces.com/production/currencies/64/ltc.webp",
      "exchanges": 125,
      "markets": 361,
      "pairs": 108,
      "categories": [],
      "allTimeHighUSD": 413.0840556096379,
      "circulatingSupply": 74199356,
      "totalSupply": 74199356,
      "maxSupply": 84000000,
      "links": {
        "website": "https://litecoin.org/",
        "whitepaper": null,
        "twitter": "https://twitter.com/litecoin",
        "reddit": "https://reddit.com/r/litecoin",
        "telegram": "https://t.me/litecoin",
        "discord": null,
        "medium": null,
        "instagram": "https://instagram.com/litecoindotcom",
        "tiktok": null,
        "youtube": null,
        "linkedin": null,
        "twitch": null,
        "spotify": null,
        "naver": null,
        "wechat": null,
        "soundcloud": null
      },
      "code": "LTC",
      "rate": 72.97163572653356,
      "volume": 331312930,
      "cap": 5414448377,
      "delta": {
        "hour": 0.9965,
        "day": 1.0171,
        "week": 1.0707,
        "month": 1.0112,
        "quarter": 1.0353,
        "year": 0.7798
      }
    },
    {
      "name": "Immutable X",
      "rank": 24,
      "age": 829,
      "color": "#13242c",
      "png32": "https://lcw.nyc3.cdn.digitaloceanspaces.com/production/currencies/32/_imx.png",
      "png64": "https://lcw.nyc3.cdn.digitaloceanspaces.com/production/currencies/64/_imx.png",
      "webp32": "https://lcw.nyc3.cdn.digitaloceanspaces.com/production/currencies/32/_imx.webp",
      "webp64": "https://lcw.nyc3.cdn.digitaloceanspaces.com/production/currencies/64/_imx.webp",
      "exchanges": 51,
      "markets": 66,
      "pairs": 14,
      "categories": [
        "smart_contract_platforms",
        "nfts",
        "gaming"
      ],
      "allTimeHighUSD": 9.49962548516342,
      "circulatingSupply": 1701419347,
      "totalSupply": 2000000000,
      "maxSupply": 2000000000,
      "links": {
        "website": "https://www.immutable.com",
        "whitepaper": "https://support.immutable.com/hc/en-us/articles/4405227590799",
        "twitter": "https://twitter.com/Immutable",
        "reddit": "https://reddit.com/r/ImmutableX",
        "telegram": "https://t.me/immutablex",
        "discord": "https://discord.com/invite/6GjgPkp464",
        "medium": "https://immutablex.medium.com/",
        "instagram": null,
        "tiktok": null,
        "youtube": null,
        "linkedin": null,
        "twitch": null,
        "spotify": null,
        "naver": null,
        "wechat": null,
        "soundcloud": null
      },
      "code": "_IMX",
      "rate": 2.942093242439243,
      "volume": 243606751,
      "cap": 5005734363,
      "delta": {
        "hour": 0.9919,
        "day": 0.9761,
        "week": 1.2916,
        "month": 1.399,
        "quarter": 2.6654,
        "year": 2.952
      }
    },
    {
      "name": "Ethereum Classic",
      "rank": 25,
      "age": 2759,
      "color": "#3ab93a",
      "png32": "https://lcw.nyc3.cdn.digitaloceanspaces.com/production/currencies/32/etc.png",
      "png64": "https://lcw.nyc3.cdn.digitaloceanspaces.com/production/currencies/64/etc.png",
      "webp32": "https://lcw.nyc3.cdn.digitaloceanspaces.com/production/currencies/32/etc.webp",
      "webp64": "https://lcw.nyc3.cdn.digitaloceanspaces.com/production/currencies/64/etc.webp",
      "exchanges": 75,
      "markets": 140,
      "pairs": 26,
      "categories": [
        "smart_contract_platforms"
      ],
      "allTimeHighUSD": 168.98136358110946,
      "circulatingSupply": 145522491,
      "totalSupply": 210700000,
      "maxSupply": 210700000,
      "links": {
        "website": "https://ethereumclassic.github.io/",
        "whitepaper": "https://github.com/ethereum/wiki/wiki/White-Paper",
        "twitter": "https://twitter.com/eth_classic",
        "reddit": "https://reddit.com/r/EthereumClassic",
        "telegram": null,
        "discord": "https://discord.com/invite/bMGuZsA",
        "medium": null,
        "instagram": null,
        "tiktok": null,
        "youtube": null,
        "linkedin": null,
        "twitch": null,
        "spotify": null,
        "naver": null,
        "wechat": null,
        "soundcloud": null
      },
      "code": "ETC",
      "rate": 27.019690231105717,
      "volume": 200265334,
      "cap": 3931972628,
      "delta": {
        "hour": 0.9938,
        "day": 1.0371,
        "week": 1.1118,
        "month": 0.9584,
        "quarter": 1.4339,
        "year": 1.2908
      }
    },
    {
      "name": "Cosmos",
      "rank": 26,
      "age": 2682,
      "color": "#30334c",
      "png32": "https://lcw.nyc3.cdn.digitaloceanspaces.com/production/currencies/32/atom.png",
      "png64": "https://lcw.nyc3.cdn.digitaloceanspaces.com/production/currencies/64/atom.png",
      "webp32": "https://lcw.nyc3.cdn.digitaloceanspaces.com/production/currencies/32/atom.webp",
      "webp64": "https://lcw.nyc3.cdn.digitaloceanspaces.com/production/currencies/64/atom.webp",
      "exchanges": 73,
      "markets": 177,
      "pairs": 66,
      "categories": [
        "iot",
        "smart_contract_platforms"
      ],
      "allTimeHighUSD": 44.477623439842205,
      "circulatingSupply": 386401441,
      "totalSupply": 386401441,
      "maxSupply": null,
      "links": {
        "website": "https://cosmos.network/",
        "whitepaper": "https://cosmos.network/resources/whitepaper",
        "twitter": "https://twitter.com/cosmos",
        "reddit": "https://reddit.com/r/cosmosnetwork",
        "telegram": "https://t.me/cosmosproject",
        "discord": "https://discord.com/invite/cosmosnetwork",
        "medium": null,
        "instagram": null,
        "tiktok": null,
        "youtube": null,
        "linkedin": null,
        "twitch": null,
        "spotify": null,
        "naver": null,
        "wechat": null,
        "soundcloud": null
      },
      "code": "ATOM",
      "rate": 9.985009750881572,
      "volume": 165384541,
      "cap": 3858222156,
      "delta": {
        "hour": 1.0053,
        "day": 1.0172,
        "week": 1.0941,
        "month": 0.9811,
        "quarter": 1.1083,
        "year": 0.7519
      }
    },
    {
      "name": "Optimism",
      "rank": 27,
      "age": 622,
      "color": "#fc0424",
      "png32": "https://lcw.nyc3.cdn.digitaloceanspaces.com/production/currencies/32/op.png",
      "png64": "https://lcw.nyc3.cdn.digitaloceanspaces.com/production/currencies/64/op.png",
      "webp32": "https://lcw.nyc3.cdn.digitaloceanspaces.com/production/currencies/32/op.webp",
      "webp64": "https://lcw.nyc3.cdn.digitaloceanspaces.com/production/currencies/64/op.webp",
      "exchanges": 49,
      "markets": 111,
      "pairs": 32,
      "categories": [
        "governance"
      ],
      "allTimeHighUSD": 4.273669842229234,
      "circulatingSupply": 957378568,
      "totalSupply": 4294967296,
      "maxSupply": null,
      "links": {
        "website": "https://app.optimism.io/announcement",
        "whitepaper": "https://community.optimism.io/",
        "twitter": "https://twitter.com/optimismPBC",
        "reddit": null,
        "telegram": null,
        "discord": "https://discord.gg/optimism",
        "medium": "https://optimismpbc.medium.com/",
        "instagram": null,
        "tiktok": null,
        "youtube": null,
        "linkedin": null,
        "twitch": "https://www.twitch.tv/optimismpbc",
        "spotify": null,
        "naver": null,
        "wechat": null,
        "soundcloud": null
      },
      "code": "OP",
      "rate": 3.814132100062858,
      "volume": 371998150,
      "cap": 3651568328,
      "delta": {
        "hour": 1.0028,
        "day": 1.0719,
        "week": 1.209,
        "month": 1.0021,
        "quarter": 2.1308,
        "year": 1.6806
      }
    },
    {
      "name": "NEAR Protocol",
      "rank": 28,
      "age": 1206,
      "color": "#040404",
      "png32": "https://lcw.nyc3.cdn.digitaloceanspaces.com/production/currencies/32/near.png",
      "png64": "https://lcw.nyc3.cdn.digitaloceanspaces.com/production/currencies/64/near.png",
      "webp32": "https://lcw.nyc3.cdn.digitaloceanspaces.com/production/currencies/32/near.webp",
      "webp64": "https://lcw.nyc3.cdn.digitaloceanspaces.com/production/currencies/64/near.webp",
      "exchanges": 69,
      "markets": 125,
      "pairs": 34,
      "categories": [
        "smart_contract_platforms"
      ],
      "allTimeHighUSD": 20.46907836312353,
      "circulatingSupply": 1034628436,
      "totalSupply": 1000000000,
      "maxSupply": 1000000000,
      "links": {
        "website": "https://near.org/",
        "whitepaper": "https://docs.near.org/docs/develop/basics/getting-started",
        "twitter": "https://twitter.com/nearprotocol",
        "reddit": "https://reddit.com/r/nearprotocol",
        "telegram": "https://t.me/cryptonear",
        "discord": "https://discord.com/invite/UY9Xf2k",
        "medium": "https://medium.com/nearprotocol",
        "instagram": "https://www.instagram.com/near_protocol",
        "tiktok": null,
        "youtube": null,
        "linkedin": null,
        "twitch": null,
        "spotify": null,
        "naver": null,
        "wechat": null,
        "soundcloud": null
      },
      "code": "NEAR",
      "rate": 3.3820861349742866,
      "volume": 396880478,
      "cap": 3499202488,
      "delta": {
        "hour": 1.0012,
        "day": 1.0378,
        "week": 1.2388,
        "month": 0.9958,
        "quarter": 2.1723,
        "year": 1.5273
      }
    },
    {
      "name": "Uniswap",
      "rank": 29,
      "age": 1243,
      "color": "#fceaf3",
      "png32": "https://lcw.nyc3.cdn.digitaloceanspaces.com/production/currencies/32/uni.png",
      "png64": "https://lcw.nyc3.cdn.digitaloceanspaces.com/production/currencies/64/uni.png",
      "webp32": "https://lcw.nyc3.cdn.digitaloceanspaces.com/production/currencies/32/uni.webp",
      "webp64": "https://lcw.nyc3.cdn.digitaloceanspaces.com/production/currencies/64/uni.webp",
      "exchanges": 103,
      "markets": 185,
      "pairs": 44,
      "categories": [
        "dex",
        "yield_farming",
        "governance"
      ],
      "allTimeHighUSD": 45.009351908031135,
      "circulatingSupply": 492695926,
      "totalSupply": 1000000000,
      "maxSupply": 1000000000,
      "links": {
        "website": "https://uniswap.org/",
        "whitepaper": "https://uniswap.org/whitepaper-v3.pdf",
        "twitter": "https://twitter.com/Uniswap",
        "reddit": "https://reddit.com/r/Uniswap",
        "telegram": null,
        "discord": "https://discord.com/invite/FCfyBSbCU5",
        "medium": null,
        "instagram": null,
        "tiktok": null,
        "youtube": null,
        "linkedin": null,
        "twitch": null,
        "spotify": null,
        "naver": null,
        "wechat": null,
        "soundcloud": null
      },
      "code": "UNI",
      "rate": 6.820770791068919,
      "volume": 91501099,
      "cap": 3360565981,
      "delta": {
        "hour": 0.9959,
        "day": 1.0184,
        "week": 1.1237,
        "month": 1.0237,
        "quarter": 1.3387,
        "year": 1.0826
      }
    },
    {
      "name": "Injective Protocol",
      "rank": 30,
      "age": 1209,
      "color": "#04a7fc",
      "png32": "https://lcw.nyc3.cdn.digitaloceanspaces.com/production/currencies/32/inj.png",
      "png64": "https://lcw.nyc3.cdn.digitaloceanspaces.com/production/currencies/64/inj.png",
      "webp32": "https://lcw.nyc3.cdn.digitaloceanspaces.com/production/currencies/32/inj.webp",
      "webp64": "https://lcw.nyc3.cdn.digitaloceanspaces.com/production/currencies/64/inj.webp",
      "exchanges": 52,
      "markets": 87,
      "pairs": 28,
      "categories": [
        "smart_contract_platforms",
        "leverage",
        "options",
        "perpetuals",
        "futures"
      ],
      "allTimeHighUSD": 45.16807651226561,
      "circulatingSupply": 88392223,
      "totalSupply": 100000000,
      "maxSupply": null,
      "links": {
        "website": "https://injectiveprotocol.com/",
        "whitepaper": "https://docs.injectiveprotocol.com/",
        "twitter": "https://twitter.com/Injective_",
        "reddit": "https://reddit.com/r/injective",
        "telegram": "https://t.me/joininjective",
        "discord": "https://discord.com/invite/NK4qdbv",
        "medium": "https://medium.com/injective-labs",
        "instagram": "https://www.instagram.com/injectivelabs/",
        "tiktok": null,
        "youtube": "https://www.youtube.com/@injective7877",
        "linkedin": null,
        "twitch": null,
        "spotify": null,
        "naver": null,
        "wechat": null,
        "soundcloud": null
      },
      "code": "INJ",
      "rate": 36.79458961342297,
      "volume": 249632448,
      "cap": 3252355570,
      "delta": {
        "hour": 0.9898,
        "day": 1.0396,
        "week": 1.1383,
        "month": 0.9363,
        "quarter": 2.317,
        "year": 11.0039
      }
    },
    {
      "name": "Kaspa",
      "rank": 31,
      "age": 627,
      "color": "#74ccbc",
      "png32": "https://lcw.nyc3.cdn.digitaloceanspaces.com/production/currencies/32/kas.png",
      "png64": "https://lcw.nyc3.cdn.digitaloceanspaces.com/production/currencies/64/kas.png",
      "webp32": "https://lcw.nyc3.cdn.digitaloceanspaces.com/production/currencies/32/kas.webp",
      "webp64": "https://lcw.nyc3.cdn.digitaloceanspaces.com/production/currencies/64/kas.webp",
      "exchanges": 20,
      "markets": 29,
      "pairs": 10,
      "categories": [
        "wallets"
      ],
      "allTimeHighUSD": 0.1547652286272869,
      "circulatingSupply": 22663662217,
      "totalSupply": 22663662217,
      "maxSupply": 28704026601,
      "links": {
        "website": "https://kaspa.org/",
        "whitepaper": "https://eprint.iacr.org/2018/104.pdf",
        "twitter": "https://twitter.com/KaspaCurrency",
        "reddit": "https://reddit.com/r/kaspa",
        "telegram": "https://t.me/Kaspaenglish",
        "discord": "https://discord.com/invite/kS3SK5F36R",
        "medium": "https://hashdag.medium.com/in-which-i-run-with-the-ghosts-of-my-hometown-95ad503c88c",
        "instagram": "https://www.instagram.com/kaspa_currency/",
        "tiktok": null,
        "youtube": "https://www.youtube.com/@kaspaCurrency",
        "linkedin": "https://www.linkedin.com/company/kaspa-currency/",
        "twitch": null,
        "spotify": null,
        "naver": null,
        "wechat": null,
        "soundcloud": null
      },
      "code": "KAS",
      "rate": 0.14196208708540745,
      "volume": 137211072,
      "cap": 3217380789,
      "delta": {
        "hour": 0.9793,
        "day": 0.9786,
        "week": 1.4242,
        "month": 1.2448,
        "quarter": 1.5524,
        "year": 21.8748
      }
    },
    {
      "name": "Stellar",
      "rank": 32,
      "age": 3478,
      "color": "#040404",
      "png32": "https://lcw.nyc3.cdn.digitaloceanspaces.com/production/currencies/32/xlm.png",
      "png64": "https://lcw.nyc3.cdn.digitaloceanspaces.com/production/currencies/64/xlm.png",
      "webp32": "https://lcw.nyc3.cdn.digitaloceanspaces.com/production/currencies/32/xlm.webp",
      "webp64": "https://lcw.nyc3.cdn.digitaloceanspaces.com/production/currencies/64/xlm.webp",
      "exchanges": 69,
      "markets": 158,
      "pairs": 45,
      "categories": [
        "smart_contract_platforms"
      ],
      "allTimeHighUSD": 0.921644339265009,
      "circulatingSupply": 28396331215,
      "totalSupply": 50001787036,
      "maxSupply": null,
      "links": {
        "website": "https://www.stellar.org",
        "whitepaper": "https://www.stellar.org/papers/stellar-consensus-protocol.pdf",
        "twitter": "https://twitter.com/StellarOrg",
        "reddit": "https://reddit.com/r/stellar",
        "telegram": null,
        "discord": null,
        "medium": "https://medium.com/stellar-community",
        "instagram": null,
        "tiktok": null,
        "youtube": null,
        "linkedin": null,
        "twitch": null,
        "spotify": null,
        "naver": null,
        "wechat": null,
        "soundcloud": null
      },
      "code": "XLM",
      "rate": 0.11319658843200876,
      "volume": 59524282,
      "cap": 3214367818,
      "delta": {
        "hour": 0.9995,
        "day": 1.0162,
        "week": 1.0435,
        "month": 0.946,
        "quarter": 0.9695,
        "year": 1.3441
      }
    },
    {
      "name": "Celestia",
      "rank": 33,
      "age": 104,
      "color": "#7b2bfc",
      "png32": "https://lcw.nyc3.cdn.digitaloceanspaces.com/production/currencies/32/_tia.png",
      "png64": "https://lcw.nyc3.cdn.digitaloceanspaces.com/production/currencies/64/_tia.png",
      "webp32": "https://lcw.nyc3.cdn.digitaloceanspaces.com/production/currencies/32/_tia.webp",
      "webp64": "https://lcw.nyc3.cdn.digitaloceanspaces.com/production/currencies/64/_tia.webp",
      "exchanges": 19,
      "markets": 26,
      "pairs": 10,
      "allTimeHighUSD": 20.887498310853765,
      "circulatingSupply": 163838048,
      "totalSupply": 1022794520,
      "maxSupply": null,
      "links": {
        "website": "https://celestia.org/",
        "whitepaper": "https://docs.celestia.org/",
        "twitter": "https://twitter.com/CelestiaOrg",
        "reddit": "https://reddit.com/r/CelestiaNetwork",
        "telegram": "https://t.me/CelestiaCommunity",
        "discord": "https://discord.com/invite/YsnTPcSfWQ",
        "medium": null,
        "instagram": null,
        "tiktok": null,
        "youtube": "https://www.youtube.com/@CelestiaNetwork",
        "linkedin": null,
        "twitch": null,
        "spotify": null,
        "naver": null,
        "wechat": null,
        "soundcloud": null
      },
      "code": "_TIA",
      "rate": 19.5904023173695,
      "volume": 131416887,
      "cap": 3209653275,
      "delta": {
        "hour": 0.9883,
        "day": 1.009,
        "week": 1.1112,
        "month": 1.0742,
        "quarter": 3.3316,
        "year": null
      }
    },
    {
      "name": "bittensor",
      "rank": 34,
      "age": 342,
      "color": "#040409",
      "png32": "https://lcw.nyc3.cdn.digitaloceanspaces.com/production/currencies/32/____tao.png",
      "png64": "https://lcw.nyc3.cdn.digitaloceanspaces.com/production/currencies/64/____tao.png",
      "webp32": "https://lcw.nyc3.cdn.digitaloceanspaces.com/production/currencies/32/____tao.webp",
      "webp64": "https://lcw.nyc3.cdn.digitaloceanspaces.com/production/currencies/64/____tao.webp",
      "exchanges": 5,
      "markets": 5,
      "pairs": 1,
      "categories": [
        "ai"
      ],
      "allTimeHighUSD": 614.5422359022967,
      "circulatingSupply": 5875690,
      "totalSupply": 5875690,
      "maxSupply": 21000000,
      "links": {
        "website": "https://bittensor.com/",
        "whitepaper": "https://docs.bittensor.com/",
        "twitter": "https://twitter.com/bittensor_",
        "reddit": "https://reddit.com/r/bittensor_",
        "telegram": "https://t.me/bittensor",
        "discord": "https://discord.com/invite/bittensor",
        "medium": "https://bittensor.medium.com/",
        "instagram": null,
        "tiktok": null,
        "youtube": "https://www.youtube.com/@Bittensor",
        "linkedin": null,
        "twitch": null,
        "spotify": null,
        "naver": null,
        "wechat": null,
        "soundcloud": null
      },
      "code": "____TAO",
      "rate": 530.6268562837383,
      "volume": 21307096,
      "cap": 3117798913,
      "delta": {
        "hour": 0.994,
        "day": 0.978,
        "week": 1.1273,
        "month": 2.3146,
        "quarter": 4.0823,
        "year": null
      }
    },
    {
      "name": "Stacks",
      "rank": 35,
      "age": 1504,
      "color": "#5546fc",
      "png32": "https://lcw.nyc3.cdn.digitaloceanspaces.com/production/currencies/32/_stx.png",
      "png64": "https://lcw.nyc3.cdn.digitaloceanspaces.com/production/currencies/64/_stx.png",
      "webp32": "https://lcw.nyc3.cdn.digitaloceanspaces.com/production/currencies/32/_stx.webp",
      "webp64": "https://lcw.nyc3.cdn.digitaloceanspaces.com/production/currencies/64/_stx.webp",
      "exchanges": 21,
      "markets": 43,
      "pairs": 17,
      "categories": [
        "smart_contract_platforms",
        "dns"
      ],
      "allTimeHighUSD": 3.205662787568635,
      "circulatingSupply": 1438964056,
      "totalSupply": 1818000000,
      "maxSupply": 1818000000,
      "links": {
        "website": "https://www.stacks.co/",
        "whitepaper": "https://docs.stacks.co/docs/intro",
        "twitter": "https://twitter.com/stacks",
        "reddit": "https://reddit.com/r/stacks",
        "telegram": "https://t.me/BlockstackChat",
        "discord": "https://discord.com/invite/zrvWsQC",
        "medium": null,
        "instagram": null,
        "tiktok": null,
        "youtube": "https://www.youtube.com/@Stacks-btc",
        "linkedin": null,
        "twitch": null,
        "spotify": null,
        "naver": null,
        "wechat": null,
        "soundcloud": null
      },
      "code": "_STX",
      "rate": 1.9964506150940948,
      "volume": 259947583,
      "cap": 2872820675,
      "delta": {
        "hour": 0.9905,
        "day": 1.0389,
        "week": 1.3429,
        "month": 1.1791,
        "quarter": 3.2242,
        "year": 6.8043
      }
    },
    {
      "name": "Filecoin",
      "rank": 36,
      "age": 1215,
      "color": "#0492fc",
      "png32": "https://lcw.nyc3.cdn.digitaloceanspaces.com/production/currencies/32/fil.png",
      "png64": "https://lcw.nyc3.cdn.digitaloceanspaces.com/production/currencies/64/fil.png",
      "webp32": "https://lcw.nyc3.cdn.digitaloceanspaces.com/production/currencies/32/fil.webp",
      "webp64": "https://lcw.nyc3.cdn.digitaloceanspaces.com/production/currencies/64/fil.webp",
      "exchanges": 44,
      "markets": 83,
      "pairs": 15,
      "categories": [
        "smart_contract_platforms",
        "storage",
        "cloud_hosting"
      ],
      "allTimeHighUSD": 237.64668979882163,
      "circulatingSupply": 507995790,
      "totalSupply": 1972610415,
      "maxSupply": 1972610415,
      "links": {
        "website": "https://filecoin.io/",
        "whitepaper": "https://docs.filecoin.io/",
        "twitter": "https://twitter.com/Filecoin",
        "reddit": "https://reddit.com/r/filecoin",
        "telegram": null,
        "discord": null,
        "medium": null,
        "instagram": null,
        "tiktok": null,
        "youtube": "https://www.youtube.com/@FilecoinProject",
        "linkedin": null,
        "twitch": null,
        "spotify": null,
        "naver": null,
        "wechat": "https://weixin.qq.com/r/1xz54Y-EctINrcuC90nF",
        "soundcloud": null
      },
      "code": "FIL",
      "rate": 5.4638890517621554,
      "volume": 126096446,
      "cap": 2775632635,
      "delta": {
        "hour": 0.9969,
        "day": 1.0232,
        "week": 1.0924,
        "month": 0.9044,
        "quarter": 1.145,
        "year": 1.1197
      }
    },
    {
      "name": "Lido DAO",
      "rank": 37,
      "age": 1133,
      "color": "#f49b8a",
      "png32": "https://lcw.nyc3.cdn.digitaloceanspaces.com/production/currencies/32/ldo.png",
      "png64": "https://lcw.nyc3.cdn.digitaloceanspaces.com/production/currencies/64/ldo.png",
      "webp32": "https://lcw.nyc3.cdn.digitaloceanspaces.com/production/currencies/32/ldo.webp",
      "webp64": "https://lcw.nyc3.cdn.digitaloceanspaces.com/production/currencies/64/ldo.webp",
      "exchanges": 56,
      "markets": 73,
      "pairs": 24,
      "categories": [
        "liquid_staking",
        "governance"
      ],
      "allTimeHighUSD": 7.327907374360521,
      "circulatingSupply": 890919128,
      "totalSupply": 1000000000,
      "maxSupply": 1000000000,
      "links": {
        "website": "https://stake.lido.fi/",
        "whitepaper": "https://docs.lido.fi/",
        "twitter": "https://twitter.com/lidofinance",
        "reddit": "https://reddit.com/r/LidoFinance",
        "telegram": "https://t.me/lidofinance",
        "discord": "https://discord.com/invite/vgdPfhZ",
        "medium": null,
        "instagram": null,
        "tiktok": null,
        "youtube": null,
        "linkedin": null,
        "twitch": null,
        "spotify": null,
        "naver": null,
        "wechat": null,
        "soundcloud": null
      },
      "code": "LDO",
      "rate": 3.103205357644667,
      "volume": 93508092,
      "cap": 2764705011,
      "delta": {
        "hour": 1.0007,
        "day": 1.0671,
        "week": 1.1527,
        "month": 0.9254,
        "quarter": 1.3471,
        "year": 1.2585
      }
    },
    {
      "name": "Hedera Hashgraph",
      "rank": 38,
      "age": 1596,
      "color": "#f8f8f8",
      "png32": "https://lcw.nyc3.cdn.digitaloceanspaces.com/production/currencies/32/hbar.png",
      "png64": "https://lcw.nyc3.cdn.digitaloceanspaces.com/production/currencies/64/hbar.png",
      "webp32": "https://lcw.nyc3.cdn.digitaloceanspaces.com/production/currencies/32/hbar.webp",
      "webp64": "https://lcw.nyc3.cdn.digitaloceanspaces.com/production/currencies/64/hbar.webp",
      "exchanges": 33,
      "markets": 64,
      "pairs": 26,
      "categories": [
        "smart_contract_platforms"
      ],
      "allTimeHighUSD": 0.569398985191319,
      "circulatingSupply": 33667358352,
      "totalSupply": 50000000000,
      "maxSupply": 50000000000,
      "links": {
        "website": "https://hedera.com/",
        "whitepaper": "https://hedera.com/papers",
        "twitter": "https://twitter.com/hedera",
        "reddit": "https://reddit.com/r/hashgraph",
        "telegram": "https://t.me/hederahashgraph",
        "discord": "https://discord.com/invite/hedera",
        "medium": "https://medium.com/hedera",
        "instagram": "https://www.instagram.com/hashgraph/",
        "tiktok": null,
        "youtube": "https://www.youtube.com/hederahashgraph",
        "linkedin": "https://www.linkedin.com/company/hashgraph/",
        "twitch": null,
        "spotify": null,
        "naver": null,
        "wechat": null,
        "soundcloud": null
      },
      "code": "HBAR",
      "rate": 0.08021438159662306,
      "volume": 50408314,
      "cap": 2700606330,
      "delta": {
        "hour": 0.9949,
        "day": 1.0203,
        "week": 1.1463,
        "month": 0.9921,
        "quarter": 1.3668,
        "year": 0.9441
      }
    },
    {
      "name": "VeChain",
      "rank": 39,
      "age": 2365,
      "color": "#6488e1",
      "png32": "https://lcw.nyc3.cdn.digitaloceanspaces.com/production/currencies/32/vet.png",
      "png64": "https://lcw.nyc3.cdn.digitaloceanspaces.com/production/currencies/64/vet.png",
      "webp32": "https://lcw.nyc3.cdn.digitaloceanspaces.com/production/currencies/32/vet.webp",
      "webp64": "https://lcw.nyc3.cdn.digitaloceanspaces.com/production/currencies/64/vet.webp",
      "exchanges": 37,
      "markets": 94,
      "pairs": 35,
      "categories": [
        "logistics",
        "ai",
        "iot",
        "smart_contract_platforms"
      ],
      "allTimeHighUSD": 0.26773718608293,
      "circulatingSupply": 72714516834,
      "totalSupply": 85985041177,
      "maxSupply": 86712634466,
      "links": {
        "website": "https://www.vechain.org/",
        "whitepaper": "https://www.vechain.org/assets/whitepaper/whitepaper-3-0.pdf",
        "twitter": "https://twitter.com/vechainofficial",
        "reddit": "https://reddit.com/r/vechain",
        "telegram": "https://t.me/vechain_official_english",
        "discord": "https://discord.com/invite/vechain",
        "medium": "https://vechainofficial.medium.com/",
        "instagram": "https://www.instagram.com/vechainfoundation_official/",
        "tiktok": null,
        "youtube": "https://www.youtube.com/@vechainofficial",
        "linkedin": "https://www.linkedin.com/company/vechain-foundation/",
        "twitch": null,
        "spotify": null,
        "naver": null,
        "wechat": null,
        "soundcloud": null
      },
      "code": "VET",
      "rate": 0.031647477857484535,
      "volume": 51039275,
      "cap": 2301231061,
      "delta": {
        "hour": 0.9931,
        "day": 1.0353,
        "week": 1.1378,
        "month": 1.0254,
        "quarter": 1.5284,
        "year": 1.3611
      }
    },
    {
      "name": "Monero",
      "rank": 40,
      "age": 3554,
      "color": "#fc6404",
      "png32": "https://lcw.nyc3.cdn.digitaloceanspaces.com/production/currencies/32/xmr.png",
      "png64": "https://lcw.nyc3.cdn.digitaloceanspaces.com/production/currencies/64/xmr.png",
      "webp32": "https://lcw.nyc3.cdn.digitaloceanspaces.com/production/currencies/32/xmr.webp",
      "webp64": "https://lcw.nyc3.cdn.digitaloceanspaces.com/production/currencies/64/xmr.webp",
      "exchanges": 34,
      "markets": 86,
      "pairs": 30,
      "categories": [
        "privacy_coins"
      ],
      "allTimeHighUSD": 516.843201123428,
      "circulatingSupply": 18396955,
      "totalSupply": 18396955,
      "maxSupply": null,
      "links": {
        "website": "http://www.monero.cc",
        "whitepaper": "https://github.com/monero-project/research-lab/blob/master/whitepaper/whitepaper.pdf",
        "twitter": "https://twitter.com/monero",
        "reddit": "https://reddit.com/r/monero",
        "telegram": "https://t.me/bitmonero",
        "discord": null,
        "medium": null,
        "instagram": null,
        "tiktok": null,
        "youtube": null,
        "linkedin": null,
        "twitch": null,
        "spotify": null,
        "naver": null,
        "wechat": null,
        "soundcloud": null
      },
      "code": "XMR",
      "rate": 123.68565190675262,
      "volume": 119022168,
      "cap": 2275439372,
      "delta": {
        "hour": 0.9948,
        "day": 1.033,
        "week": 0.7482,
        "month": 0.7948,
        "quarter": 0.765,
        "year": 0.7716
      }
    },
    {
      "name": "Cronos",
      "rank": 41,
      "age": 1797,
      "color": "#f6f7f8",
      "png32": "https://lcw.nyc3.cdn.digitaloceanspaces.com/production/currencies/32/cro.png",
      "png64": "https://lcw.nyc3.cdn.digitaloceanspaces.com/production/currencies/64/cro.png",
      "webp32": "https://lcw.nyc3.cdn.digitaloceanspaces.com/production/currencies/32/cro.webp",
      "webp64": "https://lcw.nyc3.cdn.digitaloceanspaces.com/production/currencies/64/cro.webp",
      "exchanges": 19,
      "markets": 58,
      "pairs": 36,
      "categories": [
        "cex",
        "smart_contract_platforms",
        "debit_cards",
        "wallets"
      ],
      "allTimeHighUSD": 0.9516849148075289,
      "circulatingSupply": 25263013692,
      "totalSupply": 30263013692,
      "maxSupply": null,
      "links": {
        "website": "https://www.crypto.com/",
        "whitepaper": "https://whitepaper.cronos.org/",
        "twitter": "https://twitter.com/cryptocom",
        "reddit": "https://reddit.com/r/Crypto_com",
        "telegram": "https://t.me/CryptoComOfficial",
        "discord": "https://discord.com/invite/nsp9JTC",
        "medium": "https://medium.com/@crypto.com",
        "instagram": "https://instagram.com/cryptocomofficial",
        "tiktok": null,
        "youtube": null,
        "linkedin": null,
        "twitch": null,
        "spotify": null,
        "naver": null,
        "wechat": null,
        "soundcloud": null
      },
      "code": "CRO",
      "rate": 0.08893102973525083,
      "volume": 8484226,
      "cap": 2246665822,
      "delta": {
        "hour": 1.0019,
        "day": 1.0286,
        "week": 1.0949,
        "month": 0.9839,
        "quarter": 1.031,
        "year": 1.1771
      }
    },
    {
      "name": "Mantle",
      "rank": 42,
      "age": 210,
      "color": "#f1f1f1",
      "png32": "https://lcw.nyc3.cdn.digitaloceanspaces.com/production/currencies/32/______mnt.png",
      "png64": "https://lcw.nyc3.cdn.digitaloceanspaces.com/production/currencies/64/______mnt.png",
      "webp32": "https://lcw.nyc3.cdn.digitaloceanspaces.com/production/currencies/32/______mnt.webp",
      "webp64": "https://lcw.nyc3.cdn.digitaloceanspaces.com/production/currencies/64/______mnt.webp",
      "exchanges": 13,
      "markets": 38,
      "pairs": 12,
      "categories": [
        "governance"
      ],
      "allTimeHighUSD": 0.8499357286813085,
      "circulatingSupply": 3226917893,
      "totalSupply": 6219316794,
      "maxSupply": null,
      "links": {
        "website": "https://www.mantle.xyz/",
        "whitepaper": "https://docs.mantle.xyz/governance/introduction/overview",
        "twitter": "https://twitter.com/0xMantle",
        "reddit": null,
        "telegram": "https://t.me/mantlenetwork",
        "discord": "https://discord.com/invite/0xMantle",
        "medium": null,
        "instagram": null,
        "tiktok": null,
        "youtube": null,
        "linkedin": null,
        "twitch": null,
        "spotify": null,
        "naver": null,
        "wechat": null,
        "soundcloud": null
      },
      "code": "______MNT",
      "rate": 0.6912029862176969,
      "volume": 25403835,
      "cap": 2230455284,
      "delta": {
        "hour": 1.006,
        "day": 1.0515,
        "week": 1.165,
        "month": 0.8934,
        "quarter": 1.5611,
        "year": null
      }
    },
    {
      "name": "Sui",
      "rank": 43,
      "age": 304,
      "color": "#f7fafb",
      "png32": "https://lcw.nyc3.cdn.digitaloceanspaces.com/production/currencies/32/_sui.png",
      "png64": "https://lcw.nyc3.cdn.digitaloceanspaces.com/production/currencies/64/_sui.png",
      "webp32": "https://lcw.nyc3.cdn.digitaloceanspaces.com/production/currencies/32/_sui.webp",
      "webp64": "https://lcw.nyc3.cdn.digitaloceanspaces.com/production/currencies/64/_sui.webp",
      "exchanges": 49,
      "markets": 70,
      "pairs": 12,
      "categories": [
        "smart_contract_platforms"
      ],
      "allTimeHighUSD": 1.9008732191174504,
      "circulatingSupply": 1165931966,
      "totalSupply": 10000000000,
      "maxSupply": 10000000000,
      "links": {
        "website": "https://sui.io/",
        "whitepaper": "https://docs.sui.io/",
        "twitter": "https://twitter.com/mysten_labs",
        "reddit": null,
        "telegram": null,
        "discord": "https://discord.com/invite/sui",
        "medium": "https://medium.com/mysten-labs",
        "instagram": null,
        "tiktok": null,
        "youtube": null,
        "linkedin": "https://www.linkedin.com/company/mysten-labs",
        "twitch": null,
        "spotify": null,
        "naver": null,
        "wechat": null,
        "soundcloud": null
      },
      "code": "_SUI",
      "rate": 1.792600888087704,
      "volume": 606662644,
      "cap": 2090050678,
      "delta": {
        "hour": 1.0055,
        "day": 1.0376,
        "week": 1.116,
        "month": 1.3907,
        "quarter": 3.2069,
        "year": null
      }
    },
    {
      "name": "Maker",
      "rank": 44,
      "age": 2570,
      "color": "#1cac9c",
      "png32": "https://lcw.nyc3.cdn.digitaloceanspaces.com/production/currencies/32/mkr.png",
      "png64": "https://lcw.nyc3.cdn.digitaloceanspaces.com/production/currencies/64/mkr.png",
      "webp32": "https://lcw.nyc3.cdn.digitaloceanspaces.com/production/currencies/32/mkr.webp",
      "webp64": "https://lcw.nyc3.cdn.digitaloceanspaces.com/production/currencies/64/mkr.webp",
      "exchanges": 51,
      "markets": 75,
      "pairs": 17,
      "categories": [
        "governance",
        "lending"
      ],
      "allTimeHighUSD": 6299.141412958623,
      "circulatingSupply": 977631,
      "totalSupply": 977631,
      "maxSupply": 1000000,
      "links": {
        "website": "https://makerdao.com/",
        "whitepaper": "https://makerdao.com/assets/documents/purple.pdf",
        "twitter": "https://twitter.com/MakerDAO",
        "reddit": "https://reddit.com/r/MakerDAO",
        "telegram": "https://t.me/makerdaoOfficial",
        "discord": null,
        "medium": null,
        "instagram": null,
        "tiktok": null,
        "youtube": null,
        "linkedin": null,
        "twitch": null,
        "spotify": null,
        "naver": null,
        "wechat": null,
        "soundcloud": null
      },
      "code": "MKR",
      "rate": 2087.7419331122874,
      "volume": 52887200,
      "cap": 2041041234,
      "delta": {
        "hour": 0.9999,
        "day": 1.0361,
        "week": 1.0698,
        "month": 0.9998,
        "quarter": 1.5228,
        "year": 3.0587
      }
    },
    {
      "name": "Render Token",
      "rank": 45,
      "age": 1333,
      "color": "#cedfe8",
      "png32": "https://lcw.nyc3.cdn.digitaloceanspaces.com/production/currencies/32/rndr.png",
      "png64": "https://lcw.nyc3.cdn.digitaloceanspaces.com/production/currencies/64/rndr.png",
      "webp32": "https://lcw.nyc3.cdn.digitaloceanspaces.com/production/currencies/32/rndr.webp",
      "webp64": "https://lcw.nyc3.cdn.digitaloceanspaces.com/production/currencies/64/rndr.webp",
      "exchanges": 62,
      "markets": 92,
      "pairs": 24,
      "categories": [
        "cloud_hosting"
      ],
      "allTimeHighUSD": 9.030982633537896,
      "circulatingSupply": 374733133,
      "totalSupply": 531039932,
      "maxSupply": 644245094,
      "links": {
        "website": "https://rendertoken.com/",
        "whitepaper": "https://know.rendertoken.com/",
        "twitter": "https://twitter.com/rendertoken",
        "reddit": "https://reddit.com/r/RenderToken",
        "telegram": "https://t.me/RenderTokenOfficial",
        "discord": null,
        "medium": "https://medium.com/render-token",
        "instagram": null,
        "tiktok": null,
        "youtube": "https://medium.com/render-token",
        "linkedin": null,
        "twitch": null,
        "spotify": null,
        "naver": null,
        "wechat": null,
        "soundcloud": null
      },
      "code": "RNDR",
      "rate": 4.825079871820892,
      "volume": 132184833,
      "cap": 1808117297,
      "delta": {
        "hour": 0.9999,
        "day": 1.0341,
        "week": 1.0853,
        "month": 1.237,
        "quarter": 2.152,
        "year": 3.0324
      }
    },
    {
      "name": "Sei Network",
      "rank": 46,
      "age": 182,
      "color": "#b5344f",
      "png32": "https://lcw.nyc3.cdn.digitaloceanspaces.com/production/currencies/32/sei.png",
      "png64": "https://lcw.nyc3.cdn.digitaloceanspaces.com/production/currencies/64/sei.png",
      "webp32": "https://lcw.nyc3.cdn.digitaloceanspaces.com/production/currencies/32/sei.webp",
      "webp64": "https://lcw.nyc3.cdn.digitaloceanspaces.com/production/currencies/64/sei.webp",
      "exchanges": 19,
      "markets": 31,
      "pairs": 11,
      "categories": [
        "smart_contract_platforms"
      ],
      "allTimeHighUSD": 0.8863098405234378,
      "circulatingSupply": 2175000000,
      "totalSupply": 8650409938,
      "maxSupply": 10000000000,
      "links": {
        "website": "https://www.sei.io/",
        "whitepaper": "https://docs.sei.io/",
        "twitter": "https://twitter.com/SeiNetwork",
        "reddit": "https://reddit.com/r/Sei_Network",
        "telegram": "https://t.me/seinetwork",
        "discord": "https://discord.com/invite/sei",
        "medium": null,
        "instagram": null,
        "tiktok": null,
        "youtube": null,
        "linkedin": null,
        "twitch": null,
        "spotify": null,
        "naver": null,
        "wechat": null,
        "soundcloud": null
      },
      "code": "SEI",
      "rate": 0.7464007733085706,
      "volume": 350142170,
      "cap": 1623421682,
      "delta": {
        "hour": 0.9983,
        "day": 1.0966,
        "week": 1.2133,
        "month": 1.0161,
        "quarter": 5.0959,
        "year": null
      }
    },
    {
      "name": "Bitcoin SV",
      "rank": 47,
      "age": 1921,
      "color": "#ebb304",
      "png32": "https://lcw.nyc3.cdn.digitaloceanspaces.com/production/currencies/32/bsv.png",
      "png64": "https://lcw.nyc3.cdn.digitaloceanspaces.com/production/currencies/64/bsv.png",
      "webp32": "https://lcw.nyc3.cdn.digitaloceanspaces.com/production/currencies/32/bsv.webp",
      "webp64": "https://lcw.nyc3.cdn.digitaloceanspaces.com/production/currencies/64/bsv.webp",
      "exchanges": 23,
      "markets": 38,
      "pairs": 6,
      "categories": [
        "smart_contract_platforms"
      ],
      "allTimeHighUSD": 491.46694659606356,
      "circulatingSupply": 19266076,
      "totalSupply": 19266076,
      "maxSupply": 21000000,
      "links": {
        "website": "https://bitcoinsv.io/",
        "whitepaper": null,
        "twitter": "https://twitter.com/BitcoinSVNode",
        "reddit": null,
        "telegram": null,
        "discord": null,
        "medium": null,
        "instagram": null,
        "tiktok": null,
        "youtube": null,
        "linkedin": null,
        "twitch": null,
        "spotify": null,
        "naver": null,
        "wechat": null,
        "soundcloud": null
      },
      "code": "BSV",
      "rate": 82.27187986765891,
      "volume": 59980017,
      "cap": 1585056290,
      "delta": {
        "hour": 0.9936,
        "day": 1.0298,
        "week": 1.1417,
        "month": 0.9322,
        "quarter": 1.7413,
        "year": 2.0205
      }
    },
    {
      "name": "The Graph",
      "rank": 48,
      "age": 1152,
      "color": "#453bab",
      "png32": "https://lcw.nyc3.cdn.digitaloceanspaces.com/production/currencies/32/grt.png",
      "png64": "https://lcw.nyc3.cdn.digitaloceanspaces.com/production/currencies/64/grt.png",
      "webp32": "https://lcw.nyc3.cdn.digitaloceanspaces.com/production/currencies/32/grt.webp",
      "webp64": "https://lcw.nyc3.cdn.digitaloceanspaces.com/production/currencies/64/grt.webp",
      "exchanges": 72,
      "markets": 115,
      "pairs": 26,
      "categories": [
        "analytics",
        "cloud_hosting"
      ],
      "allTimeHighUSD": 2.8886968848938896,
      "circulatingSupply": 8838119984,
      "totalSupply": 10000000000,
      "maxSupply": 10000000000,
      "links": {
        "website": "https://thegraph.com/",
        "whitepaper": "https://thegraph.com/docs/en/",
        "twitter": "https://twitter.com/graphprotocol",
        "reddit": "https://reddit.com/r/thegraph",
        "telegram": "https://t.me/graphprotocol",
        "discord": "https://discord.com/invite/vtvv7FP",
        "medium": null,
        "instagram": null,
        "tiktok": null,
        "youtube": "https://www.youtube.com/GraphProtocol",
        "linkedin": null,
        "twitch": null,
        "spotify": null,
        "naver": null,
        "wechat": null,
        "soundcloud": null
      },
      "code": "GRT",
      "rate": 0.17530022936962325,
      "volume": 65673745,
      "cap": 1549324460,
      "delta": {
        "hour": 0.9984,
        "day": 1.0379,
        "week": 1.1534,
        "month": 1.0296,
        "quarter": 1.4048,
        "year": 1.1473
      }
    },
    {
      "name": "MultiversX",
      "rank": 49,
      "age": 1257,
      "color": "#060606",
      "png32": "https://lcw.nyc3.cdn.digitaloceanspaces.com/production/currencies/32/egld.png",
      "png64": "https://lcw.nyc3.cdn.digitaloceanspaces.com/production/currencies/64/egld.png",
      "webp32": "https://lcw.nyc3.cdn.digitaloceanspaces.com/production/currencies/32/egld.webp",
      "webp64": "https://lcw.nyc3.cdn.digitaloceanspaces.com/production/currencies/64/egld.webp",
      "exchanges": 27,
      "markets": 56,
      "pairs": 25,
      "categories": [
        "smart_contract_platforms"
      ],
      "allTimeHighUSD": 548.0865877630855,
      "circulatingSupply": 26568467,
      "totalSupply": 26573619,
      "maxSupply": null,
      "links": {
        "website": "https://multiversx.com/",
        "whitepaper": "https://elrond.com/assets/files/elrond-whitepaper.pdf",
        "twitter": "https://twitter.com/MultiversX",
        "reddit": "https://reddit.com/r/elrondnetwork",
        "telegram": "https://t.me/ElrondNetwork",
        "discord": null,
        "medium": null,
        "instagram": "https://www.instagram.com/elrondnetwork/",
        "tiktok": null,
        "youtube": null,
        "linkedin": null,
        "twitch": null,
        "spotify": null,
        "naver": null,
        "wechat": null,
        "soundcloud": null
      },
      "code": "EGLD",
      "rate": 57.86760304667084,
      "volume": 35955600,
      "cap": 1537453502,
      "delta": {
        "hour": 0.9928,
        "day": 1.0072,
        "week": 1.0859,
        "month": 1.0642,
        "quarter": 1.3002,
        "year": 1.3367
      }
    },
    {
      "name": "Beam",
      "rank": 50,
      "age": 97,
      "color": "#f1af5f",
      "png32": "https://lcw.nyc3.cdn.digitaloceanspaces.com/production/currencies/32/__beam.png",
      "png64": "https://lcw.nyc3.cdn.digitaloceanspaces.com/production/currencies/64/__beam.png",
      "webp32": "https://lcw.nyc3.cdn.digitaloceanspaces.com/production/currencies/32/__beam.webp",
      "webp64": "https://lcw.nyc3.cdn.digitaloceanspaces.com/production/currencies/64/__beam.webp",
      "exchanges": 17,
      "markets": 19,
      "pairs": 6,
      "categories": [
        "smart_contract_platforms",
        "gaming",
        "nfts",
        "education",
        "governance"
      ],
      "allTimeHighUSD": 0.029693890324591233,
      "circulatingSupply": 51499421890,
      "totalSupply": 32073204963,
      "maxSupply": null,
      "links": {
        "website": "https://www.onbeam.com/",
        "whitepaper": "https://docs.onbeam.com/",
        "twitter": "https://twitter.com/MeritCircle_IO",
        "reddit": null,
        "telegram": "https://t.me/meritcircle_ann",
        "discord": "https://discord.com/invite/meritcircle",
        "medium": "https://medium.com/@meritcircle",
        "instagram": "https://www.instagram.com/meritcircle",
        "tiktok": null,
        "youtube": null,
        "linkedin": null,
        "twitch": null,
        "spotify": null,
        "naver": null,
        "wechat": null,
        "soundcloud": null
      },
      "code": "__BEAM",
      "rate": 0.02963975777970104,
      "volume": 140647325,
      "cap": 1526430391,
      "delta": {
        "hour": 1.0127,
        "day": 1.1415,
        "week": 1.7338,
        "month": 1.6061,
        "quarter": 4.2189,
        "year": null
      }
    }
  ]
